clarvynn/__init__.py
clarvynn/cli.py
clarvynn/configurator.py
clarvynn/logging.py
clarvynn/core/__init__.py
clarvynn/processors/__init__.py
clarvynn/processors/batch_exporter_adapter.py
clarvynn/processors/clarvynn_log_processor.py
clarvynn/processors/clarvynn_span_processor.py
clarvynn/processors/tracestate_exporter.py
clarvynn-0.3.1.dist-info/licenses/LICENSE
core/__init__.py
core/cpl_engine/__init__.py
core/cpl_engine/python/__init__.py
core/cpl_engine/python/base.py
core/cpl_engine/python/cpl_engine.py
core/cpl_engine/python/local_policy_cache.py
core/cpl_engine/python/log_buffer.py
core/cpl_engine/python/policy_sync_manager.py
core/cpl_engine/python/production_cpl_adapter.py
clarvynn-0.3.1.dist-info/METADATA
clarvynn-0.3.1.dist-info/WHEEL
clarvynn-0.3.1.dist-info/entry_points.txt
clarvynn-0.3.1.dist-info/top_level.txt
clarvynn-0.3.1.dist-info/RECORD
