Metadata-Version: 2.4
Name: clarvynn
Version: 0.3.1
Summary: Intelligent Deferred Head Sampling for OpenTelemetry with policy-driven governance
Author-email: Dheeraj Vanamala <dheerajvanamala@gmail.com>
Maintainer-email: Dheeraj Vanamala <dheerajvanamala@gmail.com>
License: Apache-2.0
Project-URL: Homepage, https://github.com/Clarvynn/Clarvynn
Project-URL: Documentation, https://github.com/Clarvynn/Clarvynn/tree/main/docs
Project-URL: Repository, https://github.com/Clarvynn/Clarvynn
Project-URL: Bug Tracker, https://github.com/Clarvynn/Clarvynn/issues
Project-URL: Changelog, https://github.com/Clarvynn/Clarvynn/blob/main/CHANGELOG.md
Keywords: opentelemetry,observability,sampling,tracing,logging,cost-optimization,telemetry,cpl,tail-sampling
Classifier: Development Status :: 3 - Alpha
Classifier: Intended Audience :: Developers
Classifier: Intended Audience :: System Administrators
Classifier: Operating System :: OS Independent
Classifier: Programming Language :: Python
Classifier: Programming Language :: Python :: 3
Classifier: Programming Language :: Python :: 3.9
Classifier: Programming Language :: Python :: 3.10
Classifier: Programming Language :: Python :: 3.11
Classifier: Programming Language :: Python :: 3.12
Classifier: Topic :: System :: Monitoring
Classifier: Topic :: System :: Logging
Classifier: Topic :: Software Development :: Libraries :: Python Modules
Classifier: Typing :: Typed
Requires-Python: >=3.9
License-File: LICENSE
Requires-Dist: opentelemetry-api<2.0.0,>=1.25.0
Requires-Dist: opentelemetry-sdk<2.0.0,>=1.25.0
Requires-Dist: opentelemetry-instrumentation<1.0.0,>=0.46b0
Requires-Dist: opentelemetry-exporter-otlp<2.0.0,>=1.25.0
Requires-Dist: pyyaml<7.0,>=6.0
Requires-Dist: pyparsing<4.0.0,>=3.0.0
Provides-Extra: dev
Requires-Dist: pytest>=7.4.0; extra == "dev"
Requires-Dist: pytest-cov>=4.1.0; extra == "dev"
Requires-Dist: pytest-asyncio>=0.21.0; extra == "dev"
Requires-Dist: black>=23.0.0; extra == "dev"
Requires-Dist: isort>=5.12.0; extra == "dev"
Requires-Dist: flake8>=6.0.0; extra == "dev"
Requires-Dist: mypy>=1.5.0; extra == "dev"
Requires-Dist: types-PyYAML>=6.0.0; extra == "dev"
Provides-Extra: test
Requires-Dist: flask>=2.3.0; extra == "test"
Requires-Dist: django>=4.2.0; extra == "test"
Requires-Dist: fastapi>=0.100.0; extra == "test"
Requires-Dist: uvicorn>=0.23.0; extra == "test"
Requires-Dist: opentelemetry-instrumentation-flask>=0.41b0; extra == "test"
Requires-Dist: opentelemetry-instrumentation-django>=0.41b0; extra == "test"
Requires-Dist: opentelemetry-instrumentation-fastapi>=0.41b0; extra == "test"
Provides-Extra: full
Requires-Dist: opentelemetry-exporter-otlp-proto-grpc>=1.25.0; extra == "full"
Requires-Dist: opentelemetry-exporter-prometheus>=1.25.0; extra == "full"
Requires-Dist: opentelemetry-semantic-conventions>=0.41b0; extra == "full"
Provides-Extra: all
Requires-Dist: clarvynn[dev,full,test]; extra == "all"
Dynamic: license-file
